[{"name": "EEC  311 Electric Circuits II", "cid": 2203, "sec": "100", "sess": "8W1", "begd": "05/21/22", "endd": "07/15/22", "days": ["Mon", "Wed", "Fri"], "begt": "2:00 PM", "endt": "4:05 PM", "room": "FH 314", "inst": "Dong,Lili", "comp": "LEC", "stat": true, "enrl": 5, "capc": 30, "desc": "Prerequisites: EEC 310 (C or better), ESC 250. Prerequisite or corequisite: PHY 244. Continuation of EEC 310. Polyphase AC circuits; magnetically-coupled circuits; frequency response and resonance; two-port networks; Laplace transform analysis of circuits; transfer functions, poles and zeros; convolution; Fourier series and Fourier transform analysis; integration of computer applications using PSPICE.", "Session:": " 8 Week Session - First ", "Consent:": "No Special Consent Required", "Component:": "Lecture", "Status:": "Open", "Credits:": "4.0", "Enrollment:": "5/30", "Last Day To Add:": "05/26/2022", "Last Day To Drop:": "05/31/2022", "Last Day To Withdraw:": "06/29/2022", "semester": "SUM22", "subject": "EEC"}, {"name": "EEC  313 Electronics I", "cid": 1660, "sec": "100", "sess": "8W1", "begd": "None", "endd": "None", "days": ["TBA"], "begt": "None", "endt": "None", "room": "TBA", "inst": "TBA", "comp": "LEC", "stat": false, "enrl": 0, "capc": 30, "desc": "Prerequisites: ESC 250, EEC 310. Rectifier diodes and applications; Zener diodes and applications; biasing BJT and FET amplifiers; small signal analysis of BJT and FET amplifiers; power amplifiers; amplifier frequency response.", "Session:": " 8 Week Session - First ", "Consent:": "No Special Consent Required", "Component:": "Lecture", "Status:": "Cancelled", "Credits:": "3.0", "Enrollment:": "0/30", "Last Day To Add:": "05/26/2022", "Last Day To Drop:": "05/31/2022", "Last Day To Withdraw:": "06/29/2022", "semester": "SUM22", "subject": "EEC"}, {"name": "EEC  313 Electronics I", "cid": 2383, "sec": "150", "sess": "8W1", "begd": "05/21/22", "endd": "07/15/22", "days": ["Mon", "Wed"], "begt": "6:00 PM", "endt": "8:25 PM", "room": "FH 314", "inst": "Rarick,Richard Allen", "comp": "LEC", "stat": true, "enrl": 8, "capc": 30, "desc": "Prerequisites: ESC 250, EEC 310. Rectifier diodes and applications; Zener diodes and applications; biasing BJT and FET amplifiers; small signal analysis of BJT and FET amplifiers; power amplifiers; amplifier frequency response.", "Session:": " 8 Week Session - First ", "Consent:": "No Special Consent Required", "Component:": "Lecture", "Status:": "Open", "Credits:": "3.0", "Enrollment:": "8/30", "Last Day To Add:": "05/26/2022", "Last Day To Drop:": "05/31/2022", "Last Day To Withdraw:": "06/29/2022", "semester": "SUM22", "subject": "EEC"}, {"name": "EEC  315 Electronics Lab", "cid": 2207, "sec": "100", "sess": "8W1", "begd": "05/21/22", "endd": "07/15/22", "days": ["Mon", "Wed"], "begt": "9:00 AM", "endt": "12:00 PM", "room": "WH 220", "inst": "Staff,CSU", "comp": "LAB", "stat": true, "enrl": 2, "capc": 16, "desc": "Prerequisites: EEC 311. Corequisite: EEC 313. Selected experiments on electronic circuits.", "Session:": " 8 Week Session - First ", "Consent:": "No Special Consent Required", "Component:": "Laboratory", "Status:": "Open", "Credits:": "2.0", "Enrollment:": "2/16", "Last Day To Add:": "05/26/2022", "Last Day To Drop:": "05/31/2022", "Last Day To Withdraw:": "06/29/2022", "semester": "SUM22", "subject": "EEC"}, {"name": "EEC  316 Electronic Devices Lab", "cid": 2206, "sec": "100", "sess": "8W1", "begd": "05/21/22", "endd": "07/15/22", "days": ["Mon", "Wed"], "begt": "9:00 AM", "endt": "12:00 PM", "room": "WH 220", "inst": "Staff,CSU", "comp": "LAB", "stat": true, "enrl": 7, "capc": 8, "desc": "Prerequisites: EEC 311, 313. Selected experiments on electronic circuits.", "Session:": " 8 Week Session - First ", "Consent:": "No Special Consent Required", "Component:": "Laboratory", "Status:": "Open", "Credits:": "1.0", "Enrollment:": "7/8", "Last Day To Add:": "05/26/2022", "Last Day To Drop:": "05/31/2022", "Last Day To Withdraw:": "06/29/2022", "semester": "SUM22", "subject": "EEC"}, {"name": "EEC  383 Digital Systems", "cid": 1651, "sec": "150", "sess": "8W1", "begd": "05/21/22", "endd": "07/15/22", "days": ["Mon", "Wed", "Fri"], "begt": "4:10 PM", "endt": "5:45 PM", "room": "WH 224", "inst": "Staff,CSU", "comp": "LEC", "stat": true, "enrl": 15, "capc": 30, "desc": "Pre- or co-requisite: EEC 310 or PHY 242/244.  Coverage includes binary number systems, Boolean algebra, combinational logic design principles, combinational logic design practices, finite state machine, sequential logic design principles, and sequential logic design practices.", "Session:": " 8 Week Session - First ", "Consent:": "No Special Consent Required", "Component:": "Lecture", "Status:": "Open", "Credits:": "3.0", "Enrollment:": "15/30", "Last Day To Add:": "05/26/2022", "Last Day To Drop:": "05/31/2022", "Last Day To Withdraw:": "06/29/2022", "semester": "SUM22", "subject": "EEC"}, {"name": "EEC  384 Digital Systems Laboratory", "cid": 1430, "sec": "100", "sess": "8W1", "begd": "05/21/22", "endd": "07/15/22", "days": ["Mon", "Wed", "Fri"], "begt": "10:40 AM", "endt": "12:15 PM", "room": "WH 318", "inst": "Staff,CSU", "comp": "LAB", "stat": true, "enrl": 11, "capc": 24, "desc": "Prerequisite: EEC383 or EEC 382. Selected experiments in digital systems.", "Session:": " 8 Week Session - First ", "Consent:": "No Special Consent Required", "Component:": "Laboratory", "Status:": "Open", "Credits:": "2.0", "Enrollment:": "11/24", "Last Day To Add:": "05/26/2022", "Last Day To Drop:": "05/31/2022", "Last Day To Withdraw:": "06/29/2022", "semester": "SUM22", "subject": "EEC"}, {"name": "EEC  430 Digital Signal Processing", "cid": 1652, "sec": "150", "sess": "8W1", "begd": "05/21/22", "endd": "07/15/22", "days": ["Mon", "Wed"], "begt": "6:00 PM", "endt": "9:10 PM", "room": "WH 220", "inst": "Hizlan,Murad", "comp": "LEC", "stat": false, "enrl": 15, "capc": 15, "desc": "Prerequisites: EEC 315 or 316, EEC 383. Modeling of DSP operations using discrete-time signals and systems: difference equations, Z-transforms, Fourier methods; signal sampling (A/D) and reconstruction (D/A); digital filters; sample rate converters and oversampling; DFT, and fast convolution; delta-sigma converters; selected applications. Out-of-class projects done using Matlab.", "Session:": " 8 Week Session - First ", "Consent:": "No Special Consent Required", "Component:": "Lecture", "Status:": "Closed", "Credits:": "3.0", "Enrollment:": "15/15", "Last Day To Add:": "05/26/2022", "Last Day To Drop:": "05/31/2022", "Last Day To Withdraw:": "06/29/2022", "semester": "SUM22", "subject": "EEC"}]